_cwordninja_core
cwordninja
